grmrcnn/__init__.py
grmrcnn/grmrcnn.py
grmrcnn-0.1.dist-info/AUTHORS.rst
grmrcnn-0.1.dist-info/LICENSE
grmrcnn-0.1.dist-info/METADATA
grmrcnn-0.1.dist-info/WHEEL
grmrcnn-0.1.dist-info/top_level.txt
grmrcnn-0.1.dist-info/RECORD
